bspump/__init__.py
bspump/__main__.py
bspump/__version__.py
bspump/application.py
bspump/exception.py
bspump/fileloader.py
bspump/main.py
bspump/pipeline.py
bspump/pumpbuilder.py
bspump/service.py
bspump/watch.py
bspump/abc/__init__.py
bspump/abc/anomaly.py
bspump/abc/connection.py
bspump/abc/generator.py
bspump/abc/lookup.py
bspump/abc/lookupprovider.py
bspump/abc/processor.py
bspump/abc/sink.py
bspump/abc/source.py
bspump/aggregation/__init__.py
bspump/aggregation/hyperloglog.py
bspump/aio/__init__.py
bspump/aio/sink.py
bspump/amqp/__init__.py
bspump/amqp/connection.py
bspump/amqp/sink.py
bspump/amqp/source.py
bspump/analyzer/__init__.py
bspump/analyzer/analyzer.py
bspump/analyzer/analyzingsource.py
bspump/analyzer/geoanalyzer.py
bspump/analyzer/latch.py
bspump/analyzer/sessionanalyzer.py
bspump/analyzer/threshold.py
bspump/analyzer/timedriftanalyzer.py
bspump/analyzer/timewindowanalyzer.py
bspump/anomaly/__init__.py
bspump/anomaly/analyzer.py
bspump/anomaly/generalanomaly.py
bspump/anomaly/manager.py
bspump/anomaly/storage.py
bspump/asab/__init__.py
bspump/asab/__version__.py
bspump/asab/alert.py
bspump/asab/application.py
bspump/asab/config.py
bspump/asab/exceptions.py
bspump/asab/log.py
bspump/asab/pdict.py
bspump/asab/pubsub.py
bspump/asab/socket.py
bspump/asab/task.py
bspump/asab/timer.py
bspump/asab/tls.py
bspump/asab/utils.py
bspump/asab/abc/__init__.py
bspump/asab/abc/module.py
bspump/asab/abc/service.py
bspump/asab/abc/singleton.py
bspump/asab/api/__init__.py
bspump/asab/api/discovery.py
bspump/asab/api/doc.py
bspump/asab/api/doc_templates.py
bspump/asab/api/log.py
bspump/asab/api/service.py
bspump/asab/api/web_handler.py
bspump/asab/library/__init__.py
bspump/asab/library/dirsync.py
bspump/asab/library/item.py
bspump/asab/library/service.py
bspump/asab/library/providers/__init__.py
bspump/asab/library/providers/abc.py
bspump/asab/library/providers/azurestorage.py
bspump/asab/library/providers/filesystem.py
bitswan-2025.12.12.30.dist-info/METADATA
bitswan-2025.12.12.30.dist-info/WHEEL
bitswan-2025.12.12.30.dist-info/entry_points.txt
bitswan-2025.12.12.30.dist-info/licenses/LICENSE
bitswan-2025.12.12.30.dist-info/RECORD
