Metadata-Version: 2.4
Name: bitswan
Version: 2025.12.12.30
Summary: Bitswan is a framework for building automations and pipelines in Jupyter
Project-URL: homepage, https://github.com/bitswan-space/BitSwan
Author-email: LibertyAces Ltd <timothy.hobbs@libertyaces.com>
License: BSD 3-Clause License
License-File: LICENSE
Requires-Dist: aiohttp>=3.8.3
Requires-Dist: aiomysql>=0.2.0
Requires-Dist: aiosmtplib>=1.1.3
Requires-Dist: aiozk>=0.25.0
Requires-Dist: certifi>=2023.7.22
Requires-Dist: confluent-kafka>=1.8.2
Requires-Dist: couchdb>=1.2
Requires-Dist: croniter>=1.4.1
Requires-Dist: cryptography>=44.0.1
Requires-Dist: docker
Requires-Dist: dockerfile-parse
Requires-Dist: fastapi
Requires-Dist: fastavro>=0.23.5
Requires-Dist: fastjsonschema<3,>=2.16.2
Requires-Dist: google-api-python-client>=1.7.10
Requires-Dist: idna>=3.7
Requires-Dist: importlib-resources
Requires-Dist: jinja2>=3.1.6
Requires-Dist: jupyter
Requires-Dist: kazoo<3,>=2.9.0
Requires-Dist: matplotlib>=3.8.0
Requires-Dist: mcp==1.20.0
Requires-Dist: mongoquery>=1.3.6
Requires-Dist: motor>=2.1.0
Requires-Dist: mysql-replication>=0.21
Requires-Dist: nest-asyncio==1.6.0
Requires-Dist: netaddr>=0.7.20
Requires-Dist: numpy>=1.19.0
Requires-Dist: orjson
Requires-Dist: paho-mqtt
Requires-Dist: pandas>=0.24.2
Requires-Dist: pika>=1.1.0
Requires-Dist: pyasn1==0.4.8
Requires-Dist: pybind11>=2.6.1
Requires-Dist: pyjwt==v2.10.1
Requires-Dist: pymongo>=3.10.1
Requires-Dist: pymysql>=1.1.1
Requires-Dist: python-dotenv==1.0.1
Requires-Dist: pytz>=2020.1
Requires-Dist: pyyaml>=5.4
Requires-Dist: requests>=2.32.0
Requires-Dist: setuptools>=70.0.0
Requires-Dist: urllib3>=1.26.19
Requires-Dist: uvicorn
Requires-Dist: xxhash>=1.4.4
Requires-Dist: zipp>=3.19.1
Provides-Extra: dev
Requires-Dist: coverage==4.5.3; extra == 'dev'
Requires-Dist: pytest; extra == 'dev'
Requires-Dist: pytest-asyncio; extra == 'dev'
Requires-Dist: ruff; extra == 'dev'
Requires-Dist: watchdog==6.0.0; extra == 'dev'
Provides-Extra: pyjq-support
Requires-Dist: pyjq>=2.6.0; extra == 'pyjq-support'
